zarr_audio/__init__.py
zarr_audio/encoder.py
zarr_audio/reader.py
zarr_audio-0.2.0.dist-info/licenses/LICENSE
zarr_audio-0.2.0.dist-info/METADATA
zarr_audio-0.2.0.dist-info/WHEEL
zarr_audio-0.2.0.dist-info/top_level.txt
zarr_audio-0.2.0.dist-info/RECORD
