Metadata-Version: 2.4
Name: zarr-audio
Version: 0.2.0
Summary: FLAC codec and tooling for Zarr
Author-email: Joe Weiss <joe.weiss@gmail.com>
License:                                  Apache License
Project-URL: Homepage, https://github.com/joeweiss/zarr-audio
Project-URL: Repository, https://github.com/joeweiss/zarr-audio
Project-URL: Bug Tracker, https://github.com/joeweiss/zarr-audio/issues
Keywords: zarr,audio,flac,wav,fsspec,bioacoustics,soundfile
Classifier: Development Status :: 3 - Alpha
Classifier: Intended Audience :: Science/Research
Classifier: Intended Audience :: Developers
Classifier: License :: OSI Approved :: Apache Software License
Classifier: Programming Language :: Python :: 3.9
Classifier: Programming Language :: Python :: 3.10
Classifier: Programming Language :: Python :: 3.11
Classifier: Topic :: Multimedia :: Sound/Audio
Classifier: Topic :: Scientific/Engineering :: Information Analysis
Classifier: Operating System :: OS Independent
Requires-Python: >=3.9
License-File: LICENSE
Requires-Dist: numpy
Requires-Dist: zarr<3.0.0,>=2.0.0
Requires-Dist: soundfile
Requires-Dist: librosa
Requires-Dist: numcodecs
Requires-Dist: fsspec[s3]
Requires-Dist: flac_numcodecs
Requires-Dist: pydub
Provides-Extra: dev
Requires-Dist: pytest; extra == "dev"
Requires-Dist: pytest-cov; extra == "dev"
Requires-Dist: black; extra == "dev"
Requires-Dist: isort; extra == "dev"
Requires-Dist: mypy; extra == "dev"
Requires-Dist: watchdog; extra == "dev"
Dynamic: license-file
